basilisp_blender/__init__.py
basilisp_blender/bpy_utils.lpy
basilisp_blender/control_panel.lpy
basilisp_blender/eval.py
basilisp_blender/nrepl.py
basilisp_blender/utils.lpy
basilisp_blender-0.5.0.dist-info/LICENSE
basilisp_blender-0.5.0.dist-info/LICENSE_EXTENSION
basilisp_blender-0.5.0.dist-info/METADATA
basilisp_blender-0.5.0.dist-info/WHEEL
basilisp_blender-0.5.0.dist-info/RECORD
