Metadata-Version: 2.1
Name: basilisp-blender
Version: 0.5.0
Summary: 
Home-page: https://github.com/ikappaki/basilisp-blender
Author: ikappaki
Requires-Python: >=3.9,<4.0
Classifier: Programming Language :: Python :: 3
Classifier: Programming Language :: Python :: 3.9
Classifier: Programming Language :: Python :: 3.10
Classifier: Programming Language :: Python :: 3.11
Classifier: Programming Language :: Python :: 3.12
Classifier: Programming Language :: Python :: 3.13
Requires-Dist: basilisp (>=0.4.0)
Requires-Dist: basilisp-nrepl-async (>=0.1.1)
